gbot/__init__.py
gbot/boolean_operations.py
gbot/bsplines.py
gbot/divided_difference.py
gbot/draggablepoints.py
gbot/transformations.py
gbot-0.0.2.dist-info/LICENSE
gbot-0.0.2.dist-info/METADATA
gbot-0.0.2.dist-info/WHEEL
gbot-0.0.2.dist-info/top_level.txt
gbot-0.0.2.dist-info/RECORD
